adgmlclass/__init__.py
adgmlclass-0.0.6.dist-info/METADATA
adgmlclass-0.0.6.dist-info/WHEEL
adgmlclass-0.0.6.dist-info/top_level.txt
adgmlclass-0.0.6.dist-info/RECORD
