Metadata-Version: 2.1
Name: adgmlclass
Version: 0.0.6
Summary: A class used for finding the best machine learning algorithm
Home-page: https://www.adgstudios.co.za
Author: Ashlin Darius Govindasamy
Author-email: adgrules@hotmail.com
License: MIT
Platform: UNKNOWN
Classifier: Programming Language :: Python :: 3
Classifier: License :: OSI Approved :: MIT License
Classifier: Operating System :: OS Independent
Requires-Dist: click
Requires-Dist: pytz
Requires-Dist: pandas
Requires-Dist: numpy
Requires-Dist: matplotlib
Requires-Dist: seaborn
Requires-Dist: scikit-learn
